Telethroid/__init__.py
Telethroid/client/__init__.py
Telethroid/client/telethroid.py
Telethroid/filters/__init__.py
Telethroid/filters/filters.py
Telethroid/types/__init__.py
Telethroid/types/inlinebuttons.py
Telethroid/types/message.py
Telethroid/types/reply_markup.py
Telethroid-0.0.28.dist-info/COPYING
Telethroid-0.0.28.dist-info/METADATA
Telethroid-0.0.28.dist-info/WHEEL
Telethroid-0.0.28.dist-info/top_level.txt
Telethroid-0.0.28.dist-info/RECORD
